mclabs/__init__.py
mclabs/extra_symbols/curated-icons-index.json
mclabs/extra_symbols/by-category/ai-ml/Agent-Assist.png
mclabs/extra_symbols/by-category/ai-ml/Analytics-Hub.png
mclabs/extra_symbols/by-category/ai-ml/Data-QnA.png
mclabs/extra_symbols/by-category/ai-ml/Data-Studio.png
mclabs/extra_symbols/by-category/ai-ml/Dataplex.png
mclabs/extra_symbols/by-category/ai-ml/Dialogflow.png
mclabs/extra_symbols/by-category/ai-ml/Looker.png
mclabs/extra_symbols/by-category/ai-ml/Vertex-AI.png
mclabs/extra_symbols/by-category/data-integration-databases/Cloud-SQL.png
mclabs/extra_symbols/by-category/data-integration-databases/Database-Migration-Service.png
mclabs/extra_symbols/by-category/data-integration-databases/Datastream.png
mclabs/extra_symbols/by-category/devops-ci-cd/Artifact-Registry.png
mclabs/extra_symbols/by-category/devops-ci-cd/Batch.png
mclabs/extra_symbols/by-category/devops-ci-cd/Cloud-Deploy.png
mclabs/extra_symbols/by-category/devops-ci-cd/Configuration-Management.png
mclabs/extra_symbols/by-category/devops-ci-cd/Migrate-For-Anthos.png
mclabs/extra_symbols/by-category/management-operations/Billing.png
mclabs/extra_symbols/by-category/management-operations/Cloud-Monitoring.png
mclabs/extra_symbols/by-category/maps/Google-Maps-Platform.png
mclabs/extra_symbols/by-category/network-edge-cdn/Cloud-CDN.png
mclabs/extra_symbols/by-category/network-edge-cdn/Network-Topology.png
mclabs/extra_symbols/by-category/security-identity/Beyondcorp.png
mclabs/gcp_diagram_mcp_server/__init__.py
mclabs/gcp_diagram_mcp_server/diagrams_tools.py
mclabs/gcp_diagram_mcp_server/models.py
mclabs/gcp_diagram_mcp_server/scanner.py
mclabs/gcp_diagram_mcp_server/server.py
mclabs_gcp_diagram_mcp_server-1.0.6.dist-info/METADATA
mclabs_gcp_diagram_mcp_server-1.0.6.dist-info/WHEEL
mclabs_gcp_diagram_mcp_server-1.0.6.dist-info/entry_points.txt
mclabs_gcp_diagram_mcp_server-1.0.6.dist-info/licenses/LICENSE
mclabs_gcp_diagram_mcp_server-1.0.6.dist-info/licenses/NOTICE
mclabs_gcp_diagram_mcp_server-1.0.6.dist-info/RECORD
