Metadata-Version: 2.4
Name: mclabs.gcp-diagram-mcp-server
Version: 1.0.6
Summary: An MCP server that seamlessly creates GCP diagrams using the Python diagrams package DSL
Project-URL: Homepage, https://mclabs.github.io/mcp/
Project-URL: Documentation, https://mclabs.github.io/mcp/servers/gcp-diagram-mcp-server/
Project-URL: Source, https://github.com/mclabs/mcp.git
Project-URL: Bug Tracker, https://github.com/mclabs/mcp/issues
Project-URL: Changelog, https://github.com/mclabs/mcp/blob/main/src/gcp-diagram-mcp-server/CHANGELOG.md
Author: MCLabs
Author-email: MCLabs MCP <mclabs-mcp@example.com>
License-Expression: Apache-2.0
License-File: LICENSE
License-File: NOTICE
Classifier: License :: OSI Approved :: Apache Software License
Classifier: Operating System :: OS Independent
Classifier: Programming Language :: Python
Classifier: Programming Language :: Python :: 3
Classifier: Programming Language :: Python :: 3.10
Classifier: Programming Language :: Python :: 3.11
Classifier: Programming Language :: Python :: 3.12
Classifier: Programming Language :: Python :: 3.13
Requires-Python: >=3.10
Requires-Dist: bandit>=1.7.5
Requires-Dist: diagrams>=0.24.4
Requires-Dist: mcp[cli]>=1.11.0
Requires-Dist: pydantic>=2.10.6
Requires-Dist: setuptools>=78.1.1
Requires-Dist: starlette>=0.47.2
Requires-Dist: urllib3>=2.5.0
